raiderio_async/__init__.py
raiderio_async/raiderio_async.py
raiderio_async-1.3.0.dist-info/LICENSE
raiderio_async-1.3.0.dist-info/METADATA
raiderio_async-1.3.0.dist-info/WHEEL
raiderio_async-1.3.0.dist-info/RECORD
